COPYRIGHT
MANIFEST.in
Makefile
README
setup.py
test/__init__.py
test/__init__.pyc
test/test_compile.py
test/test_filter.py
test/__pycache__/test_compile.cpython-27-PYTEST.pyc
test/__pycache__/test_filter.cpython-27-PYTEST.pyc
tiddlywebplugins/__init__.py
tiddlywebplugins/policyfilter.py
tiddlywebplugins.policyfilter.egg-info/PKG-INFO
tiddlywebplugins.policyfilter.egg-info/SOURCES.txt
tiddlywebplugins.policyfilter.egg-info/dependency_links.txt
tiddlywebplugins.policyfilter.egg-info/namespace_packages.txt
tiddlywebplugins.policyfilter.egg-info/not-zip-safe
tiddlywebplugins.policyfilter.egg-info/requires.txt
tiddlywebplugins.policyfilter.egg-info/top_level.txt