Metadata-Version: 1.0
Name: tiddlywebplugins.policyfilter
Version: 0.1
Summary: Filter bags and recipes based on policy
Home-page: http://pypi.python.org/pypi/tiddlywebplugins.policyfilter
Author: Chris Dent
Author-email: cdent@peermore.com
License: UNKNOWN
Platform: Posix; MacOS X; Windows
